[{"id": "Aberdeen City and Aberdeenshire", "year": 1998, "gdp_per_head": 18923.0}, {"id": "Aberdeen City and Aberdeenshire", "year": 1999, "gdp_per_head": 18866.0}, {"id": "Aberdeen City and Aberdeenshire", "year": 2000, "gdp_per_head": 19361.0}, {"id": "Aberdeen City and Aberdeenshire", "year": 2001, "gdp_per_head": 20855.0}, {"id": "Aberdeen City and Aberdeenshire", "year": 2002, "gdp_per_head": 21848.0}, {"id": "Aberdeen City and Aberdeenshire", "year": 2003, "gdp_per_head": 22038.0}, {"id": "Aberdeen City and Aberdeenshire", "year": 2004, "gdp_per_head": 23069.0}, {"id": "Aberdeen City and Aberdeenshire", "year": 2005, "gdp_per_head": 24117.0}, {"id": "Aberdeen City and Aberdeenshire", "year": 2006, "gdp_per_head": 27297.0}, {"id": "Aberdeen City and Aberdeenshire", "year": 2007, "gdp_per_head": 29945.0}, {"id": "Aberdeen City and Aberdeenshire", "year": 2008, "gdp_per_head": 32685.0}, {"id": "Aberdeen City and Aberdeenshire", "year": 2009, "gdp_per_head": 32285.0}, {"id": "Aberdeen City and Aberdeenshire", "year": 2010, "gdp_per_head": 32808.0}, {"id": "Aberdeen City and Aberdeenshire", "year": 2011, "gdp_per_head": 33282.0}, {"id": "Aberdeen City and Aberdeenshire", "year": 2012, "gdp_per_head": 34990.0}, {"id": "Aberdeen City and Aberdeenshire", "year": 2013, "gdp_per_head": 36940.0}, {"id": "Aberdeen City and Aberdeenshire", "year": 2014, "gdp_per_head": 38235.0}, {"id": "Aberdeen City and Aberdeenshire", "year": 2015, "gdp_per_head": 37034.0}, {"id": "Aberdeen City and Aberdeenshire", "year": 2016, "gdp_per_head": 34017.0}, {"id": "Aberdeen City and Aberdeenshire", "year": 2017, "gdp_per_head": 33881.0}, {"id": "Aberdeen City and Aberdeenshire", "year": 2018, "gdp_per_head": 34738.0}, {"id": "Aberdeen City and Aberdeenshire", "year": 2019, "gdp_per_head": 35203.0}, {"id": "Caithness & Sutherland and Ross & Cromarty", "year": 1998, "gdp_per_head": 11279.0}, {"id": "Caithness & Sutherland and Ross & Cromarty", "year": 1999, "gdp_per_head": 11858.0}, {"id": "Caithness & Sutherland and Ross & Cromarty", "year": 2000, "gdp_per_head": 12330.0}, {"id": "Caithness & Sutherland and Ross & Cromarty", "year": 2001, "gdp_per_head": 12828.0}, {"id": "Caithness & Sutherland and Ross & Cromarty", "year": 2002, "gdp_per_head": 13179.0}, {"id": "Caithness & Sutherland and Ross & Cromarty", "year": 2003, "gdp_per_head": 14479.0}, {"id": "Caithness & Sutherland and Ross & Cromarty", "year": 2004, "gdp_per_head": 15261.0}, {"id": "Caithness & Sutherland and Ross & Cromarty", "year": 2005, "gdp_per_head": 15782.0}, {"id": "Caithness & Sutherland and Ross & Cromarty", "year": 2006, "gdp_per_head": 16578.0}, {"id": "Caithness & Sutherland and Ross & Cromarty", "year": 2007, "gdp_per_head": 16759.0}, {"id": "Caithness & Sutherland and Ross & Cromarty", "year": 2008, "gdp_per_head": 17335.0}, {"id": "Caithness & Sutherland and Ross & Cromarty", "year": 2009, "gdp_per_head": 16908.0}, {"id": "Caithness & Sutherland and Ross & Cromarty", "year": 2010, "gdp_per_head": 16937.0}, {"id": "Caithness & Sutherland and Ross & Cromarty", "year": 2011, "gdp_per_head": 17968.0}, {"id": "Caithness & Sutherland and Ross & Cromarty", "year": 2012, "gdp_per_head": 18610.0}, {"id": "Caithness & Sutherland and Ross & Cromarty", "year": 2013, "gdp_per_head": 19064.0}, {"id": "Caithness & Sutherland and Ross & Cromarty", "year": 2014, "gdp_per_head": 20135.0}, {"id": "Caithness & Sutherland and Ross & Cromarty", "year": 2015, "gdp_per_head": 19683.0}, {"id": "Caithness & Sutherland and Ross & Cromarty", "year": 2016, "gdp_per_head": 19750.0}, {"id": "Caithness & Sutherland and Ross & Cromarty", "year": 2017, "gdp_per_head": 21009.0}, {"id": "Caithness & Sutherland and Ross & Cromarty", "year": 2018, "gdp_per_head": 21475.0}, {"id": "Caithness & Sutherland and Ross & Cromarty", "year": 2019, "gdp_per_head": 22325.0}, {"id": "Inverness & Nairn and Moray, Badenoch & Strathspey", "year": 1998, "gdp_per_head": 13306.0}, {"id": "Inverness & Nairn and Moray, Badenoch & Strathspey", "year": 1999, "gdp_per_head": 13689.0}, {"id": "Inverness & Nairn and Moray, Badenoch & Strathspey", "year": 2000, "gdp_per_head": 13976.0}, {"id": "Inverness & Nairn and Moray, Badenoch & Strathspey", "year": 2001, "gdp_per_head": 14346.0}, {"id": "Inverness & Nairn and Moray, Badenoch & Strathspey", "year": 2002, "gdp_per_head": 14602.0}, {"id": "Inverness & Nairn and Moray, Badenoch & Strathspey", "year": 2003, "gdp_per_head": 15694.0}, {"id": "Inverness & Nairn and Moray, Badenoch & Strathspey", "year": 2004, "gdp_per_head": 16654.0}, {"id": "Inverness & Nairn and Moray, Badenoch & Strathspey", "year": 2005, "gdp_per_head": 17383.0}, {"id": "Inverness & Nairn and Moray, Badenoch & Strathspey", "year": 2006, "gdp_per_head": 18220.0}, {"id": "Inverness & Nairn and Moray, Badenoch & Strathspey", "year": 2007, "gdp_per_head": 18732.0}, {"id": "Inverness & Nairn and Moray, Badenoch & Strathspey", "year": 2008, "gdp_per_head": 19949.0}, {"id": "Inverness & Nairn and Moray, Badenoch & Strathspey", "year": 2009, "gdp_per_head": 19749.0}, {"id": "Inverness & Nairn and Moray, Badenoch & Strathspey", "year": 2010, "gdp_per_head": 20508.0}, {"id": "Inverness & Nairn and Moray, Badenoch & Strathspey", "year": 2011, "gdp_per_head": 21513.0}, {"id": "Inverness & Nairn and Moray, Badenoch & Strathspey", "year": 2012, "gdp_per_head": 21556.0}, {"id": "Inverness & Nairn and Moray, Badenoch & Strathspey", "year": 2013, "gdp_per_head": 22841.0}, {"id": "Inverness & Nairn and Moray, Badenoch & Strathspey", "year": 2014, "gdp_per_head": 23347.0}, {"id": "Inverness & Nairn and Moray, Badenoch & Strathspey", "year": 2015, "gdp_per_head": 23858.0}, {"id": "Inverness & Nairn and Moray, Badenoch & Strathspey", "year": 2016, "gdp_per_head": 23955.0}, {"id": "Inverness & Nairn and Moray, Badenoch & Strathspey", "year": 2017, "gdp_per_head": 25794.0}, {"id": "Inverness & Nairn and Moray, Badenoch & Strathspey", "year": 2018, "gdp_per_head": 26384.0}, {"id": "Inverness & Nairn and Moray, Badenoch & Strathspey", "year": 2019, "gdp_per_head": 27447.0}, {"id": "Lochaber, Skye & Lochalsh, Arran & Cumbrae and Argyll & Bute", "year": 1998, "gdp_per_head": 11254.0}, {"id": "Lochaber, Skye & Lochalsh, Arran & Cumbrae and Argyll & Bute", "year": 1999, "gdp_per_head": 12082.0}, {"id": "Lochaber, Skye & Lochalsh, Arran & Cumbrae and Argyll & Bute", "year": 2000, "gdp_per_head": 12573.0}, {"id": "Lochaber, Skye & Lochalsh, Arran & Cumbrae and Argyll & Bute", "year": 2001, "gdp_per_head": 13564.0}, {"id": "Lochaber, Skye & Lochalsh, Arran & Cumbrae and Argyll & Bute", "year": 2002, "gdp_per_head": 13882.0}, {"id": "Lochaber, Skye & Lochalsh, Arran & Cumbrae and Argyll & Bute", "year": 2003, "gdp_per_head": 15314.0}, {"id": "Lochaber, Skye & Lochalsh, Arran & Cumbrae and Argyll & Bute", "year": 2004, "gdp_per_head": 16401.0}, {"id": "Lochaber, Skye & Lochalsh, Arran & Cumbrae and Argyll & Bute", "year": 2005, "gdp_per_head": 17647.0}, {"id": "Lochaber, Skye & Lochalsh, Arran & Cumbrae and Argyll & Bute", "year": 2006, "gdp_per_head": 18492.0}, {"id": "Lochaber, Skye & Lochalsh, Arran & Cumbrae and Argyll & Bute", "year": 2007, "gdp_per_head": 18578.0}, {"id": "Lochaber, Skye & Lochalsh, Arran & Cumbrae and Argyll & Bute", "year": 2008, "gdp_per_head": 19378.0}, {"id": "Lochaber, Skye & Lochalsh, Arran & Cumbrae and Argyll & Bute", "year": 2009, "gdp_per_head": 19272.0}, {"id": "Lochaber, Skye & Lochalsh, Arran & Cumbrae and Argyll & Bute", "year": 2010, "gdp_per_head": 18939.0}, {"id": "Lochaber, Skye & Lochalsh, Arran & Cumbrae and Argyll & Bute", "year": 2011, "gdp_per_head": 19449.0}, {"id": "Lochaber, Skye & Lochalsh, Arran & Cumbrae and Argyll & Bute", "year": 2012, "gdp_per_head": 19908.0}, {"id": "Lochaber, Skye & Lochalsh, Arran & Cumbrae and Argyll & Bute", "year": 2013, "gdp_per_head": 20242.0}, {"id": "Lochaber, Skye & Lochalsh, Arran & Cumbrae and Argyll & Bute", "year": 2014, "gdp_per_head": 20957.0}, {"id": "Lochaber, Skye & Lochalsh, Arran & Cumbrae and Argyll & Bute", "year": 2015, "gdp_per_head": 21430.0}, {"id": "Lochaber, Skye & Lochalsh, Arran & Cumbrae and Argyll & Bute", "year": 2016, "gdp_per_head": 22196.0}, {"id": "Lochaber, Skye & Lochalsh, Arran & Cumbrae and Argyll & Bute", "year": 2017, "gdp_per_head": 24059.0}, {"id": "Lochaber, Skye & Lochalsh, Arran & Cumbrae and Argyll & Bute", "year": 2018, "gdp_per_head": 24113.0}, {"id": "Lochaber, Skye & Lochalsh, Arran & Cumbrae and Argyll & Bute", "year": 2019, "gdp_per_head": 24994.0}, {"id": "Na h-Eileanan Siar (Western Isles)", "year": 1998, "gdp_per_head": 9711.0}, {"id": "Na h-Eileanan Siar (Western Isles)", "year": 1999, "gdp_per_head": 10529.0}, {"id": "Na h-Eileanan Siar (Western Isles)", "year": 2000, "gdp_per_head": 10902.0}, {"id": "Na h-Eileanan Siar (Western Isles)", "year": 2001, "gdp_per_head": 12038.0}, {"id": "Na h-Eileanan Siar (Western Isles)", "year": 2002, "gdp_per_head": 12247.0}, {"id": "Na h-Eileanan Siar (Western Isles)", "year": 2003, "gdp_per_head": 13439.0}, {"id": "Na h-Eileanan Siar (Western Isles)", "year": 2004, "gdp_per_head": 14415.0}, {"id": "Na h-Eileanan Siar (Western Isles)", "year": 2005, "gdp_per_head": 15284.0}, {"id": "Na h-Eileanan Siar (Western Isles)", "year": 2006, "gdp_per_head": 15760.0}, {"id": "Na h-Eileanan Siar (Western Isles)", "year": 2007, "gdp_per_head": 16022.0}, {"id": "Na h-Eileanan Siar (Western Isles)", "year": 2008, "gdp_per_head": 16981.0}, {"id": "Na h-Eileanan Siar (Western Isles)", "year": 2009, "gdp_per_head": 16938.0}, {"id": "Na h-Eileanan Siar (Western Isles)", "year": 2010, "gdp_per_head": 17376.0}, {"id": "Na h-Eileanan Siar (Western Isles)", "year": 2011, "gdp_per_head": 18070.0}, {"id": "Na h-Eileanan Siar (Western Isles)", "year": 2012, "gdp_per_head": 17995.0}, {"id": "Na h-Eileanan Siar (Western Isles)", "year": 2013, "gdp_per_head": 17777.0}, {"id": "Na h-Eileanan Siar (Western Isles)", "year": 2014, "gdp_per_head": 18698.0}, {"id": "Na h-Eileanan Siar (Western Isles)", "year": 2015, "gdp_per_head": 18381.0}, {"id": "Na h-Eileanan Siar (Western Isles)", "year": 2016, "gdp_per_head": 18503.0}, {"id": "Na h-Eileanan Siar (Western Isles)", "year": 2017, "gdp_per_head": 19134.0}, {"id": "Na h-Eileanan Siar (Western Isles)", "year": 2018, "gdp_per_head": 19761.0}, {"id": "Na h-Eileanan Siar (Western Isles)", "year": 2019, "gdp_per_head": 21158.0}, {"id": "Orkney Islands", "year": 1998, "gdp_per_head": 14955.0}, {"id": "Orkney Islands", "year": 1999, "gdp_per_head": 15980.0}, {"id": "Orkney Islands", "year": 2000, "gdp_per_head": 16892.0}, {"id": "Orkney Islands", "year": 2001, "gdp_per_head": 17919.0}, {"id": "Orkney Islands", "year": 2002, "gdp_per_head": 18076.0}, {"id": "Orkney Islands", "year": 2003, "gdp_per_head": 19683.0}, {"id": "Orkney Islands", "year": 2004, "gdp_per_head": 21244.0}, {"id": "Orkney Islands", "year": 2005, "gdp_per_head": 22739.0}, {"id": "Orkney Islands", "year": 2006, "gdp_per_head": 23127.0}, {"id": "Orkney Islands", "year": 2007, "gdp_per_head": 23763.0}, {"id": "Orkney Islands", "year": 2008, "gdp_per_head": 25033.0}, {"id": "Orkney Islands", "year": 2009, "gdp_per_head": 25549.0}, {"id": "Orkney Islands", "year": 2010, "gdp_per_head": 25725.0}, {"id": "Orkney Islands", "year": 2011, "gdp_per_head": 26934.0}, {"id": "Orkney Islands", "year": 2012, "gdp_per_head": 26680.0}, {"id": "Orkney Islands", "year": 2013, "gdp_per_head": 25154.0}, {"id": "Orkney Islands", "year": 2014, "gdp_per_head": 25866.0}, {"id": "Orkney Islands", "year": 2015, "gdp_per_head": 26561.0}, {"id": "Orkney Islands", "year": 2016, "gdp_per_head": 25880.0}, {"id": "Orkney Islands", "year": 2017, "gdp_per_head": 25522.0}, {"id": "Orkney Islands", "year": 2018, "gdp_per_head": 24994.0}, {"id": "Orkney Islands", "year": 2019, "gdp_per_head": 25139.0}, {"id": "Shetland Islands", "year": 1998, "gdp_per_head": 16997.0}, {"id": "Shetland Islands", "year": 1999, "gdp_per_head": 17729.0}, {"id": "Shetland Islands", "year": 2000, "gdp_per_head": 17740.0}, {"id": "Shetland Islands", "year": 2001, "gdp_per_head": 18838.0}, {"id": "Shetland Islands", "year": 2002, "gdp_per_head": 19101.0}, {"id": "Shetland Islands", "year": 2003, "gdp_per_head": 20343.0}, {"id": "Shetland Islands", "year": 2004, "gdp_per_head": 21880.0}, {"id": "Shetland Islands", "year": 2005, "gdp_per_head": 22979.0}, {"id": "Shetland Islands", "year": 2006, "gdp_per_head": 24493.0}, {"id": "Shetland Islands", "year": 2007, "gdp_per_head": 24404.0}, {"id": "Shetland Islands", "year": 2008, "gdp_per_head": 26262.0}, {"id": "Shetland Islands", "year": 2009, "gdp_per_head": 28388.0}, {"id": "Shetland Islands", "year": 2010, "gdp_per_head": 27828.0}, {"id": "Shetland Islands", "year": 2011, "gdp_per_head": 30073.0}, {"id": "Shetland Islands", "year": 2012, "gdp_per_head": 30467.0}, {"id": "Shetland Islands", "year": 2013, "gdp_per_head": 31873.0}, {"id": "Shetland Islands", "year": 2014, "gdp_per_head": 34295.0}, {"id": "Shetland Islands", "year": 2015, "gdp_per_head": 32106.0}, {"id": "Shetland Islands", "year": 2016, "gdp_per_head": 31033.0}, {"id": "Shetland Islands", "year": 2017, "gdp_per_head": 33154.0}, {"id": "Shetland Islands", "year": 2018, "gdp_per_head": 32990.0}, {"id": "Shetland Islands", "year": 2019, "gdp_per_head": 32618.0}, {"id": "Angus and Dundee City", "year": 1998, "gdp_per_head": 10999.0}, {"id": "Angus and Dundee City", "year": 1999, "gdp_per_head": 11209.0}, {"id": "Angus and Dundee City", "year": 2000, "gdp_per_head": 12056.0}, {"id": "Angus and Dundee City", "year": 2001, "gdp_per_head": 12509.0}, {"id": "Angus and Dundee City", "year": 2002, "gdp_per_head": 13071.0}, {"id": "Angus and Dundee City", "year": 2003, "gdp_per_head": 14026.0}, {"id": "Angus and Dundee City", "year": 2004, "gdp_per_head": 14570.0}, {"id": "Angus and Dundee City", "year": 2005, "gdp_per_head": 14946.0}, {"id": "Angus and Dundee City", "year": 2006, "gdp_per_head": 15826.0}, {"id": "Angus and Dundee City", "year": 2007, "gdp_per_head": 16321.0}, {"id": "Angus and Dundee City", "year": 2008, "gdp_per_head": 16591.0}, {"id": "Angus and Dundee City", "year": 2009, "gdp_per_head": 16330.0}, {"id": "Angus and Dundee City", "year": 2010, "gdp_per_head": 16416.0}, {"id": "Angus and Dundee City", "year": 2011, "gdp_per_head": 16735.0}, {"id": "Angus and Dundee City", "year": 2012, "gdp_per_head": 17368.0}, {"id": "Angus and Dundee City", "year": 2013, "gdp_per_head": 17927.0}, {"id": "Angus and Dundee City", "year": 2014, "gdp_per_head": 18790.0}, {"id": "Angus and Dundee City", "year": 2015, "gdp_per_head": 18878.0}, {"id": "Angus and Dundee City", "year": 2016, "gdp_per_head": 19362.0}, {"id": "Angus and Dundee City", "year": 2017, "gdp_per_head": 19786.0}, {"id": "Angus and Dundee City", "year": 2018, "gdp_per_head": 20514.0}, {"id": "Angus and Dundee City", "year": 2019, "gdp_per_head": 21338.0}, {"id": "Clackmannanshire and Fife", "year": 1998, "gdp_per_head": 10817.0}, {"id": "Clackmannanshire and Fife", "year": 1999, "gdp_per_head": 10986.0}, {"id": "Clackmannanshire and Fife", "year": 2000, "gdp_per_head": 11358.0}, {"id": "Clackmannanshire and Fife", "year": 2001, "gdp_per_head": 11568.0}, {"id": "Clackmannanshire and Fife", "year": 2002, "gdp_per_head": 12117.0}, {"id": "Clackmannanshire and Fife", "year": 2003, "gdp_per_head": 12794.0}, {"id": "Clackmannanshire and Fife", "year": 2004, "gdp_per_head": 13258.0}, {"id": "Clackmannanshire and Fife", "year": 2005, "gdp_per_head": 13648.0}, {"id": "Clackmannanshire and Fife", "year": 2006, "gdp_per_head": 14857.0}, {"id": "Clackmannanshire and Fife", "year": 2007, "gdp_per_head": 15366.0}, {"id": "Clackmannanshire and Fife", "year": 2008, "gdp_per_head": 15974.0}, {"id": "Clackmannanshire and Fife", "year": 2009, "gdp_per_head": 15586.0}, {"id": "Clackmannanshire and Fife", "year": 2010, "gdp_per_head": 15637.0}, {"id": "Clackmannanshire and Fife", "year": 2011, "gdp_per_head": 15712.0}, {"id": "Clackmannanshire and Fife", "year": 2012, "gdp_per_head": 16234.0}, {"id": "Clackmannanshire and Fife", "year": 2013, "gdp_per_head": 16735.0}, {"id": "Clackmannanshire and Fife", "year": 2014, "gdp_per_head": 17618.0}, {"id": "Clackmannanshire and Fife", "year": 2015, "gdp_per_head": 18288.0}, {"id": "Clackmannanshire and Fife", "year": 2016, "gdp_per_head": 18852.0}, {"id": "Clackmannanshire and Fife", "year": 2017, "gdp_per_head": 19294.0}, {"id": "Clackmannanshire and Fife", "year": 2018, "gdp_per_head": 19496.0}, {"id": "Clackmannanshire and Fife", "year": 2019, "gdp_per_head": 19979.0}, {"id": "East Lothian and Midlothian", "year": 1998, "gdp_per_head": 8508.0}, {"id": "East Lothian and Midlothian", "year": 1999, "gdp_per_head": 8640.0}, {"id": "East Lothian and Midlothian", "year": 2000, "gdp_per_head": 9071.0}, {"id": "East Lothian and Midlothian", "year": 2001, "gdp_per_head": 9321.0}, {"id": "East Lothian and Midlothian", "year": 2002, "gdp_per_head": 9801.0}, {"id": "East Lothian and Midlothian", "year": 2003, "gdp_per_head": 10456.0}, {"id": "East Lothian and Midlothian", "year": 2004, "gdp_per_head": 10880.0}, {"id": "East Lothian and Midlothian", "year": 2005, "gdp_per_head": 11252.0}, {"id": "East Lothian and Midlothian", "year": 2006, "gdp_per_head": 11868.0}, {"id": "East Lothian and Midlothian", "year": 2007, "gdp_per_head": 12196.0}, {"id": "East Lothian and Midlothian", "year": 2008, "gdp_per_head": 12330.0}, {"id": "East Lothian and Midlothian", "year": 2009, "gdp_per_head": 11989.0}, {"id": "East Lothian and Midlothian", "year": 2010, "gdp_per_head": 12090.0}, {"id": "East Lothian and Midlothian", "year": 2011, "gdp_per_head": 12397.0}, {"id": "East Lothian and Midlothian", "year": 2012, "gdp_per_head": 12928.0}, {"id": "East Lothian and Midlothian", "year": 2013, "gdp_per_head": 14183.0}, {"id": "East Lothian and Midlothian", "year": 2014, "gdp_per_head": 14817.0}, {"id": "East Lothian and Midlothian", "year": 2015, "gdp_per_head": 15339.0}, {"id": "East Lothian and Midlothian", "year": 2016, "gdp_per_head": 15733.0}, {"id": "East Lothian and Midlothian", "year": 2017, "gdp_per_head": 16266.0}, {"id": "East Lothian and Midlothian", "year": 2018, "gdp_per_head": 16871.0}, {"id": "East Lothian and Midlothian", "year": 2019, "gdp_per_head": 17625.0}, {"id": "Edinburgh, City of", "year": 1998, "gdp_per_head": 20879.0}, {"id": "Edinburgh, City of", "year": 1999, "gdp_per_head": 20868.0}, {"id": "Edinburgh, City of", "year": 2000, "gdp_per_head": 22301.0}, {"id": "Edinburgh, City of", "year": 2001, "gdp_per_head": 23856.0}, {"id": "Edinburgh, City of", "year": 2002, "gdp_per_head": 25816.0}, {"id": "Edinburgh, City of", "year": 2003, "gdp_per_head": 28401.0}, {"id": "Edinburgh, City of", "year": 2004, "gdp_per_head": 30670.0}, {"id": "Edinburgh, City of", "year": 2005, "gdp_per_head": 32702.0}, {"id": "Edinburgh, City of", "year": 2006, "gdp_per_head": 33773.0}, {"id": "Edinburgh, City of", "year": 2007, "gdp_per_head": 35931.0}, {"id": "Edinburgh, City of", "year": 2008, "gdp_per_head": 35614.0}, {"id": "Edinburgh, City of", "year": 2009, "gdp_per_head": 36347.0}, {"id": "Edinburgh, City of", "year": 2010, "gdp_per_head": 35318.0}, {"id": "Edinburgh, City of", "year": 2011, "gdp_per_head": 35240.0}, {"id": "Edinburgh, City of", "year": 2012, "gdp_per_head": 36648.0}, {"id": "Edinburgh, City of", "year": 2013, "gdp_per_head": 38113.0}, {"id": "Edinburgh, City of", "year": 2014, "gdp_per_head": 38949.0}, {"id": "Edinburgh, City of", "year": 2015, "gdp_per_head": 39336.0}, {"id": "Edinburgh, City of", "year": 2016, "gdp_per_head": 42171.0}, {"id": "Edinburgh, City of", "year": 2017, "gdp_per_head": 43508.0}, {"id": "Edinburgh, City of", "year": 2018, "gdp_per_head": 45108.0}, {"id": "Edinburgh, City of", "year": 2019, "gdp_per_head": 46027.0}, {"id": "Falkirk", "year": 1998, "gdp_per_head": 14188.0}, {"id": "Falkirk", "year": 1999, "gdp_per_head": 13953.0}, {"id": "Falkirk", "year": 2000, "gdp_per_head": 14600.0}, {"id": "Falkirk", "year": 2001, "gdp_per_head": 14885.0}, {"id": "Falkirk", "year": 2002, "gdp_per_head": 15558.0}, {"id": "Falkirk", "year": 2003, "gdp_per_head": 16562.0}, {"id": "Falkirk", "year": 2004, "gdp_per_head": 17084.0}, {"id": "Falkirk", "year": 2005, "gdp_per_head": 18672.0}, {"id": "Falkirk", "year": 2006, "gdp_per_head": 20263.0}, {"id": "Falkirk", "year": 2007, "gdp_per_head": 19579.0}, {"id": "Falkirk", "year": 2008, "gdp_per_head": 20494.0}, {"id": "Falkirk", "year": 2009, "gdp_per_head": 20546.0}, {"id": "Falkirk", "year": 2010, "gdp_per_head": 20184.0}, {"id": "Falkirk", "year": 2011, "gdp_per_head": 20288.0}, {"id": "Falkirk", "year": 2012, "gdp_per_head": 20587.0}, {"id": "Falkirk", "year": 2013, "gdp_per_head": 21298.0}, {"id": "Falkirk", "year": 2014, "gdp_per_head": 21963.0}, {"id": "Falkirk", "year": 2015, "gdp_per_head": 23351.0}, {"id": "Falkirk", "year": 2016, "gdp_per_head": 23164.0}, {"id": "Falkirk", "year": 2017, "gdp_per_head": 23327.0}, {"id": "Falkirk", "year": 2018, "gdp_per_head": 24655.0}, {"id": "Falkirk", "year": 2019, "gdp_per_head": 24947.0}, {"id": "Perth & Kinross and Stirling", "year": 1998, "gdp_per_head": 15224.0}, {"id": "Perth & Kinross and Stirling", "year": 1999, "gdp_per_head": 14881.0}, {"id": "Perth & Kinross and Stirling", "year": 2000, "gdp_per_head": 14985.0}, {"id": "Perth & Kinross and Stirling", "year": 2001, "gdp_per_head": 15614.0}, {"id": "Perth & Kinross and Stirling", "year": 2002, "gdp_per_head": 16571.0}, {"id": "Perth & Kinross and Stirling", "year": 2003, "gdp_per_head": 17812.0}, {"id": "Perth & Kinross and Stirling", "year": 2004, "gdp_per_head": 18708.0}, {"id": "Perth & Kinross and Stirling", "year": 2005, "gdp_per_head": 19618.0}, {"id": "Perth & Kinross and Stirling", "year": 2006, "gdp_per_head": 21163.0}, {"id": "Perth & Kinross and Stirling", "year": 2007, "gdp_per_head": 22122.0}, {"id": "Perth & Kinross and Stirling", "year": 2008, "gdp_per_head": 21983.0}, {"id": "Perth & Kinross and Stirling", "year": 2009, "gdp_per_head": 22577.0}, {"id": "Perth & Kinross and Stirling", "year": 2010, "gdp_per_head": 21721.0}, {"id": "Perth & Kinross and Stirling", "year": 2011, "gdp_per_head": 22075.0}, {"id": "Perth & Kinross and Stirling", "year": 2012, "gdp_per_head": 23385.0}, {"id": "Perth & Kinross and Stirling", "year": 2013, "gdp_per_head": 25102.0}, {"id": "Perth & Kinross and Stirling", "year": 2014, "gdp_per_head": 25699.0}, {"id": "Perth & Kinross and Stirling", "year": 2015, "gdp_per_head": 26107.0}, {"id": "Perth & Kinross and Stirling", "year": 2016, "gdp_per_head": 25858.0}, {"id": "Perth & Kinross and Stirling", "year": 2017, "gdp_per_head": 26938.0}, {"id": "Perth & Kinross and Stirling", "year": 2018, "gdp_per_head": 26883.0}, {"id": "Perth & Kinross and Stirling", "year": 2019, "gdp_per_head": 28302.0}, {"id": "West Lothian", "year": 1998, "gdp_per_head": 16857.0}, {"id": "West Lothian", "year": 1999, "gdp_per_head": 17312.0}, {"id": "West Lothian", "year": 2000, "gdp_per_head": 17319.0}, {"id": "West Lothian", "year": 2001, "gdp_per_head": 17487.0}, {"id": "West Lothian", "year": 2002, "gdp_per_head": 18215.0}, {"id": "West Lothian", "year": 2003, "gdp_per_head": 19420.0}, {"id": "West Lothian", "year": 2004, "gdp_per_head": 20481.0}, {"id": "West Lothian", "year": 2005, "gdp_per_head": 20564.0}, {"id": "West Lothian", "year": 2006, "gdp_per_head": 21573.0}, {"id": "West Lothian", "year": 2007, "gdp_per_head": 22364.0}, {"id": "West Lothian", "year": 2008, "gdp_per_head": 23348.0}, {"id": "West Lothian", "year": 2009, "gdp_per_head": 22116.0}, {"id": "West Lothian", "year": 2010, "gdp_per_head": 22784.0}, {"id": "West Lothian", "year": 2011, "gdp_per_head": 23014.0}, {"id": "West Lothian", "year": 2012, "gdp_per_head": 21737.0}, {"id": "West Lothian", "year": 2013, "gdp_per_head": 21326.0}, {"id": "West Lothian", "year": 2014, "gdp_per_head": 22377.0}, {"id": "West Lothian", "year": 2015, "gdp_per_head": 23742.0}, {"id": "West Lothian", "year": 2016, "gdp_per_head": 24020.0}, {"id": "West Lothian", "year": 2017, "gdp_per_head": 24858.0}, {"id": "West Lothian", "year": 2018, "gdp_per_head": 26039.0}, {"id": "West Lothian", "year": 2019, "gdp_per_head": 26917.0}, {"id": "East Dunbartonshire, West Dunbartonshire and Helensburgh & Lomond", "year": 1998, "gdp_per_head": 7955.0}, {"id": "East Dunbartonshire, West Dunbartonshire and Helensburgh & Lomond", "year": 1999, "gdp_per_head": 8193.0}, {"id": "East Dunbartonshire, West Dunbartonshire and Helensburgh & Lomond", "year": 2000, "gdp_per_head": 8520.0}, {"id": "East Dunbartonshire, West Dunbartonshire and Helensburgh & Lomond", "year": 2001, "gdp_per_head": 9073.0}, {"id": "East Dunbartonshire, West Dunbartonshire and Helensburgh & Lomond", "year": 2002, "gdp_per_head": 9413.0}, {"id": "East Dunbartonshire, West Dunbartonshire and Helensburgh & Lomond", "year": 2003, "gdp_per_head": 9941.0}, {"id": "East Dunbartonshire, West Dunbartonshire and Helensburgh & Lomond", "year": 2004, "gdp_per_head": 10663.0}, {"id": "East Dunbartonshire, West Dunbartonshire and Helensburgh & Lomond", "year": 2005, "gdp_per_head": 11531.0}, {"id": "East Dunbartonshire, West Dunbartonshire and Helensburgh & Lomond", "year": 2006, "gdp_per_head": 12116.0}, {"id": "East Dunbartonshire, West Dunbartonshire and Helensburgh & Lomond", "year": 2007, "gdp_per_head": 12181.0}, {"id": "East Dunbartonshire, West Dunbartonshire and Helensburgh & Lomond", "year": 2008, "gdp_per_head": 12819.0}, {"id": "East Dunbartonshire, West Dunbartonshire and Helensburgh & Lomond", "year": 2009, "gdp_per_head": 12612.0}, {"id": "East Dunbartonshire, West Dunbartonshire and Helensburgh & Lomond", "year": 2010, "gdp_per_head": 12597.0}, {"id": "East Dunbartonshire, West Dunbartonshire and Helensburgh & Lomond", "year": 2011, "gdp_per_head": 13025.0}, {"id": "East Dunbartonshire, West Dunbartonshire and Helensburgh & Lomond", "year": 2012, "gdp_per_head": 13195.0}, {"id": "East Dunbartonshire, West Dunbartonshire and Helensburgh & Lomond", "year": 2013, "gdp_per_head": 13494.0}, {"id": "East Dunbartonshire, West Dunbartonshire and Helensburgh & Lomond", "year": 2014, "gdp_per_head": 14044.0}, {"id": "East Dunbartonshire, West Dunbartonshire and Helensburgh & Lomond", "year": 2015, "gdp_per_head": 14316.0}, {"id": "East Dunbartonshire, West Dunbartonshire and Helensburgh & Lomond", "year": 2016, "gdp_per_head": 14806.0}, {"id": "East Dunbartonshire, West Dunbartonshire and Helensburgh & Lomond", "year": 2017, "gdp_per_head": 15621.0}, {"id": "East Dunbartonshire, West Dunbartonshire and Helensburgh & Lomond", "year": 2018, "gdp_per_head": 16361.0}, {"id": "East Dunbartonshire, West Dunbartonshire and Helensburgh & Lomond", "year": 2019, "gdp_per_head": 16860.0}, {"id": "Glasgow City", "year": 1998, "gdp_per_head": 18477.0}, {"id": "Glasgow City", "year": 1999, "gdp_per_head": 18977.0}, {"id": "Glasgow City", "year": 2000, "gdp_per_head": 19658.0}, {"id": "Glasgow City", "year": 2001, "gdp_per_head": 20919.0}, {"id": "Glasgow City", "year": 2002, "gdp_per_head": 21671.0}, {"id": "Glasgow City", "year": 2003, "gdp_per_head": 23245.0}, {"id": "Glasgow City", "year": 2004, "gdp_per_head": 25075.0}, {"id": "Glasgow City", "year": 2005, "gdp_per_head": 27319.0}, {"id": "Glasgow City", "year": 2006, "gdp_per_head": 28723.0}, {"id": "Glasgow City", "year": 2007, "gdp_per_head": 29722.0}, {"id": "Glasgow City", "year": 2008, "gdp_per_head": 30488.0}, {"id": "Glasgow City", "year": 2009, "gdp_per_head": 30128.0}, {"id": "Glasgow City", "year": 2010, "gdp_per_head": 29023.0}, {"id": "Glasgow City", "year": 2011, "gdp_per_head": 29581.0}, {"id": "Glasgow City", "year": 2012, "gdp_per_head": 30068.0}, {"id": "Glasgow City", "year": 2013, "gdp_per_head": 31397.0}, {"id": "Glasgow City", "year": 2014, "gdp_per_head": 32074.0}, {"id": "Glasgow City", "year": 2015, "gdp_per_head": 31961.0}, {"id": "Glasgow City", "year": 2016, "gdp_per_head": 32239.0}, {"id": "Glasgow City", "year": 2017, "gdp_per_head": 33358.0}, {"id": "Glasgow City", "year": 2018, "gdp_per_head": 33699.0}, {"id": "Glasgow City", "year": 2019, "gdp_per_head": 35032.0}, {"id": "Inverclyde, East Renfrewshire and Renfrewshire", "year": 1998, "gdp_per_head": 10863.0}, {"id": "Inverclyde, East Renfrewshire and Renfrewshire", "year": 1999, "gdp_per_head": 10826.0}, {"id": "Inverclyde, East Renfrewshire and Renfrewshire", "year": 2000, "gdp_per_head": 11375.0}, {"id": "Inverclyde, East Renfrewshire and Renfrewshire", "year": 2001, "gdp_per_head": 11856.0}, {"id": "Inverclyde, East Renfrewshire and Renfrewshire", "year": 2002, "gdp_per_head": 12466.0}, {"id": "Inverclyde, East Renfrewshire and Renfrewshire", "year": 2003, "gdp_per_head": 12944.0}, {"id": "Inverclyde, East Renfrewshire and Renfrewshire", "year": 2004, "gdp_per_head": 13724.0}, {"id": "Inverclyde, East Renfrewshire and Renfrewshire", "year": 2005, "gdp_per_head": 14178.0}, {"id": "Inverclyde, East Renfrewshire and Renfrewshire", "year": 2006, "gdp_per_head": 14959.0}, {"id": "Inverclyde, East Renfrewshire and Renfrewshire", "year": 2007, "gdp_per_head": 14647.0}, {"id": "Inverclyde, East Renfrewshire and Renfrewshire", "year": 2008, "gdp_per_head": 15566.0}, {"id": "Inverclyde, East Renfrewshire and Renfrewshire", "year": 2009, "gdp_per_head": 15172.0}, {"id": "Inverclyde, East Renfrewshire and Renfrewshire", "year": 2010, "gdp_per_head": 14997.0}, {"id": "Inverclyde, East Renfrewshire and Renfrewshire", "year": 2011, "gdp_per_head": 15404.0}, {"id": "Inverclyde, East Renfrewshire and Renfrewshire", "year": 2012, "gdp_per_head": 15628.0}, {"id": "Inverclyde, East Renfrewshire and Renfrewshire", "year": 2013, "gdp_per_head": 16222.0}, {"id": "Inverclyde, East Renfrewshire and Renfrewshire", "year": 2014, "gdp_per_head": 17455.0}, {"id": "Inverclyde, East Renfrewshire and Renfrewshire", "year": 2015, "gdp_per_head": 18042.0}, {"id": "Inverclyde, East Renfrewshire and Renfrewshire", "year": 2016, "gdp_per_head": 17801.0}, {"id": "Inverclyde, East Renfrewshire and Renfrewshire", "year": 2017, "gdp_per_head": 18751.0}, {"id": "Inverclyde, East Renfrewshire and Renfrewshire", "year": 2018, "gdp_per_head": 18929.0}, {"id": "Inverclyde, East Renfrewshire and Renfrewshire", "year": 2019, "gdp_per_head": 19449.0}, {"id": "North Lanarkshire", "year": 1998, "gdp_per_head": 11092.0}, {"id": "North Lanarkshire", "year": 1999, "gdp_per_head": 11214.0}, {"id": "North Lanarkshire", "year": 2000, "gdp_per_head": 11624.0}, {"id": "North Lanarkshire", "year": 2001, "gdp_per_head": 12331.0}, {"id": "North Lanarkshire", "year": 2002, "gdp_per_head": 12801.0}, {"id": "North Lanarkshire", "year": 2003, "gdp_per_head": 13428.0}, {"id": "North Lanarkshire", "year": 2004, "gdp_per_head": 14068.0}, {"id": "North Lanarkshire", "year": 2005, "gdp_per_head": 14815.0}, {"id": "North Lanarkshire", "year": 2006, "gdp_per_head": 15551.0}, {"id": "North Lanarkshire", "year": 2007, "gdp_per_head": 15599.0}, {"id": "North Lanarkshire", "year": 2008, "gdp_per_head": 16490.0}, {"id": "North Lanarkshire", "year": 2009, "gdp_per_head": 16101.0}, {"id": "North Lanarkshire", "year": 2010, "gdp_per_head": 16162.0}, {"id": "North Lanarkshire", "year": 2011, "gdp_per_head": 16436.0}, {"id": "North Lanarkshire", "year": 2012, "gdp_per_head": 16978.0}, {"id": "North Lanarkshire", "year": 2013, "gdp_per_head": 17738.0}, {"id": "North Lanarkshire", "year": 2014, "gdp_per_head": 20039.0}, {"id": "North Lanarkshire", "year": 2015, "gdp_per_head": 20327.0}, {"id": "North Lanarkshire", "year": 2016, "gdp_per_head": 20844.0}, {"id": "North Lanarkshire", "year": 2017, "gdp_per_head": 22176.0}, {"id": "North Lanarkshire", "year": 2018, "gdp_per_head": 22615.0}, {"id": "North Lanarkshire", "year": 2019, "gdp_per_head": 23699.0}, {"id": "Scottish Borders", "year": 1998, "gdp_per_head": 12459.0}, {"id": "Scottish Borders", "year": 1999, "gdp_per_head": 12406.0}, {"id": "Scottish Borders", "year": 2000, "gdp_per_head": 12782.0}, {"id": "Scottish Borders", "year": 2001, "gdp_per_head": 13164.0}, {"id": "Scottish Borders", "year": 2002, "gdp_per_head": 13633.0}, {"id": "Scottish Borders", "year": 2003, "gdp_per_head": 14016.0}, {"id": "Scottish Borders", "year": 2004, "gdp_per_head": 14396.0}, {"id": "Scottish Borders", "year": 2005, "gdp_per_head": 14469.0}, {"id": "Scottish Borders", "year": 2006, "gdp_per_head": 15444.0}, {"id": "Scottish Borders", "year": 2007, "gdp_per_head": 15448.0}, {"id": "Scottish Borders", "year": 2008, "gdp_per_head": 15936.0}, {"id": "Scottish Borders", "year": 2009, "gdp_per_head": 15620.0}, {"id": "Scottish Borders", "year": 2010, "gdp_per_head": 15615.0}, {"id": "Scottish Borders", "year": 2011, "gdp_per_head": 16137.0}, {"id": "Scottish Borders", "year": 2012, "gdp_per_head": 16452.0}, {"id": "Scottish Borders", "year": 2013, "gdp_per_head": 17346.0}, {"id": "Scottish Borders", "year": 2014, "gdp_per_head": 18641.0}, {"id": "Scottish Borders", "year": 2015, "gdp_per_head": 18932.0}, {"id": "Scottish Borders", "year": 2016, "gdp_per_head": 19142.0}, {"id": "Scottish Borders", "year": 2017, "gdp_per_head": 19474.0}, {"id": "Scottish Borders", "year": 2018, "gdp_per_head": 20413.0}, {"id": "Scottish Borders", "year": 2019, "gdp_per_head": 20844.0}, {"id": "Dumfries & Galloway", "year": 1998, "gdp_per_head": 12891.0}, {"id": "Dumfries & Galloway", "year": 1999, "gdp_per_head": 13277.0}, {"id": "Dumfries & Galloway", "year": 2000, "gdp_per_head": 14031.0}, {"id": "Dumfries & Galloway", "year": 2001, "gdp_per_head": 14815.0}, {"id": "Dumfries & Galloway", "year": 2002, "gdp_per_head": 15324.0}, {"id": "Dumfries & Galloway", "year": 2003, "gdp_per_head": 16082.0}, {"id": "Dumfries & Galloway", "year": 2004, "gdp_per_head": 16636.0}, {"id": "Dumfries & Galloway", "year": 2005, "gdp_per_head": 16911.0}, {"id": "Dumfries & Galloway", "year": 2006, "gdp_per_head": 18108.0}, {"id": "Dumfries & Galloway", "year": 2007, "gdp_per_head": 18146.0}, {"id": "Dumfries & Galloway", "year": 2008, "gdp_per_head": 19014.0}, {"id": "Dumfries & Galloway", "year": 2009, "gdp_per_head": 18797.0}, {"id": "Dumfries & Galloway", "year": 2010, "gdp_per_head": 18301.0}, {"id": "Dumfries & Galloway", "year": 2011, "gdp_per_head": 18916.0}, {"id": "Dumfries & Galloway", "year": 2012, "gdp_per_head": 19438.0}, {"id": "Dumfries & Galloway", "year": 2013, "gdp_per_head": 20568.0}, {"id": "Dumfries & Galloway", "year": 2014, "gdp_per_head": 21545.0}, {"id": "Dumfries & Galloway", "year": 2015, "gdp_per_head": 21439.0}, {"id": "Dumfries & Galloway", "year": 2016, "gdp_per_head": 21979.0}, {"id": "Dumfries & Galloway", "year": 2017, "gdp_per_head": 22848.0}, {"id": "Dumfries & Galloway", "year": 2018, "gdp_per_head": 23332.0}, {"id": "Dumfries & Galloway", "year": 2019, "gdp_per_head": 24252.0}, {"id": "East Ayrshire and North Ayrshire mainland", "year": 1998, "gdp_per_head": 9102.0}, {"id": "East Ayrshire and North Ayrshire mainland", "year": 1999, "gdp_per_head": 9406.0}, {"id": "East Ayrshire and North Ayrshire mainland", "year": 2000, "gdp_per_head": 9782.0}, {"id": "East Ayrshire and North Ayrshire mainland", "year": 2001, "gdp_per_head": 10122.0}, {"id": "East Ayrshire and North Ayrshire mainland", "year": 2002, "gdp_per_head": 10306.0}, {"id": "East Ayrshire and North Ayrshire mainland", "year": 2003, "gdp_per_head": 10750.0}, {"id": "East Ayrshire and North Ayrshire mainland", "year": 2004, "gdp_per_head": 11130.0}, {"id": "East Ayrshire and North Ayrshire mainland", "year": 2005, "gdp_per_head": 11902.0}, {"id": "East Ayrshire and North Ayrshire mainland", "year": 2006, "gdp_per_head": 12756.0}, {"id": "East Ayrshire and North Ayrshire mainland", "year": 2007, "gdp_per_head": 13030.0}, {"id": "East Ayrshire and North Ayrshire mainland", "year": 2008, "gdp_per_head": 13507.0}, {"id": "East Ayrshire and North Ayrshire mainland", "year": 2009, "gdp_per_head": 13381.0}, {"id": "East Ayrshire and North Ayrshire mainland", "year": 2010, "gdp_per_head": 13321.0}, {"id": "East Ayrshire and North Ayrshire mainland", "year": 2011, "gdp_per_head": 13413.0}, {"id": "East Ayrshire and North Ayrshire mainland", "year": 2012, "gdp_per_head": 13888.0}, {"id": "East Ayrshire and North Ayrshire mainland", "year": 2013, "gdp_per_head": 14254.0}, {"id": "East Ayrshire and North Ayrshire mainland", "year": 2014, "gdp_per_head": 14669.0}, {"id": "East Ayrshire and North Ayrshire mainland", "year": 2015, "gdp_per_head": 14749.0}, {"id": "East Ayrshire and North Ayrshire mainland", "year": 2016, "gdp_per_head": 15300.0}, {"id": "East Ayrshire and North Ayrshire mainland", "year": 2017, "gdp_per_head": 15774.0}, {"id": "East Ayrshire and North Ayrshire mainland", "year": 2018, "gdp_per_head": 15696.0}, {"id": "East Ayrshire and North Ayrshire mainland", "year": 2019, "gdp_per_head": 16122.0}, {"id": "South Ayrshire", "year": 1998, "gdp_per_head": 12226.0}, {"id": "South Ayrshire", "year": 1999, "gdp_per_head": 12485.0}, {"id": "South Ayrshire", "year": 2000, "gdp_per_head": 13409.0}, {"id": "South Ayrshire", "year": 2001, "gdp_per_head": 14025.0}, {"id": "South Ayrshire", "year": 2002, "gdp_per_head": 14725.0}, {"id": "South Ayrshire", "year": 2003, "gdp_per_head": 15332.0}, {"id": "South Ayrshire", "year": 2004, "gdp_per_head": 16124.0}, {"id": "South Ayrshire", "year": 2005, "gdp_per_head": 16835.0}, {"id": "South Ayrshire", "year": 2006, "gdp_per_head": 17867.0}, {"id": "South Ayrshire", "year": 2007, "gdp_per_head": 17532.0}, {"id": "South Ayrshire", "year": 2008, "gdp_per_head": 18206.0}, {"id": "South Ayrshire", "year": 2009, "gdp_per_head": 18255.0}, {"id": "South Ayrshire", "year": 2010, "gdp_per_head": 18543.0}, {"id": "South Ayrshire", "year": 2011, "gdp_per_head": 18778.0}, {"id": "South Ayrshire", "year": 2012, "gdp_per_head": 18351.0}, {"id": "South Ayrshire", "year": 2013, "gdp_per_head": 18425.0}, {"id": "South Ayrshire", "year": 2014, "gdp_per_head": 19357.0}, {"id": "South Ayrshire", "year": 2015, "gdp_per_head": 19705.0}, {"id": "South Ayrshire", "year": 2016, "gdp_per_head": 20058.0}, {"id": "South Ayrshire", "year": 2017, "gdp_per_head": 21101.0}, {"id": "South Ayrshire", "year": 2018, "gdp_per_head": 21680.0}, {"id": "South Ayrshire", "year": 2019, "gdp_per_head": 22043.0}, {"id": "South Lanarkshire", "year": 1998, "gdp_per_head": 11555.0}, {"id": "South Lanarkshire", "year": 1999, "gdp_per_head": 11724.0}, {"id": "South Lanarkshire", "year": 2000, "gdp_per_head": 11970.0}, {"id": "South Lanarkshire", "year": 2001, "gdp_per_head": 12463.0}, {"id": "South Lanarkshire", "year": 2002, "gdp_per_head": 12999.0}, {"id": "South Lanarkshire", "year": 2003, "gdp_per_head": 13717.0}, {"id": "South Lanarkshire", "year": 2004, "gdp_per_head": 14327.0}, {"id": "South Lanarkshire", "year": 2005, "gdp_per_head": 15259.0}, {"id": "South Lanarkshire", "year": 2006, "gdp_per_head": 16558.0}, {"id": "South Lanarkshire", "year": 2007, "gdp_per_head": 16649.0}, {"id": "South Lanarkshire", "year": 2008, "gdp_per_head": 17603.0}, {"id": "South Lanarkshire", "year": 2009, "gdp_per_head": 17409.0}, {"id": "South Lanarkshire", "year": 2010, "gdp_per_head": 17077.0}, {"id": "South Lanarkshire", "year": 2011, "gdp_per_head": 17338.0}, {"id": "South Lanarkshire", "year": 2012, "gdp_per_head": 17774.0}, {"id": "South Lanarkshire", "year": 2013, "gdp_per_head": 18739.0}, {"id": "South Lanarkshire", "year": 2014, "gdp_per_head": 19345.0}, {"id": "South Lanarkshire", "year": 2015, "gdp_per_head": 19524.0}, {"id": "South Lanarkshire", "year": 2016, "gdp_per_head": 19759.0}, {"id": "South Lanarkshire", "year": 2017, "gdp_per_head": 20966.0}, {"id": "South Lanarkshire", "year": 2018, "gdp_per_head": 21099.0}, {"id": "South Lanarkshire", "year": 2019, "gdp_per_head": 21358.0}]