{"config": {"view": {"continuousWidth": 300, "continuousHeight": 300, "stroke": null}, "font": "Circular Std Book"}, "layer": [{"mark": {"type": "line", "color": "#b4c8d8", "opacity": 0.3, "strokeWidth": 1}, "data": {"name": "data-f14e0a1e1aeb5bf7618cf53004727dc9"}, "encoding": {"x": {"axis": {"domainColor": "#b4c8d8", "domainOpacity": 0.5, "format": "%Y", "grid": false, "labelAngle": 0, "labelColor": "#b4c8d8", "labelOpacity": 0.7, "orient": "bottom", "tickColor": "#b4c8d8", "tickCount": 5, "tickOpacity": 0.5, "title": "", "titleAlign": "center", "titleAnchor": "middle", "titleColor": "#b4c8d8", "titleFontSize": 12, "titleOpacity": 0.8, "titleX": 207, "titleY": -15}, "field": "x", "sort": [], "type": "temporal"}, "y": {"axis": {"domainColor": "#b4c8d8", "domainOpacity": 0.5, "format": ".0f", "gridColor": "#b4c8d8", "gridDash": [1, 5], "gridOpacity": 0.5, "labelColor": "#b4c8d8", "labelOpacity": 0.7, "labelPadding": 5, "tickColor": "#b4c8d8", "tickCount": 8, "tickOpacity": 0.5, "ticks": false, "title": "Index, 2019 = 100", "titleAlign": "left", "titleAngle": 0, "titleBaseline": "bottom", "titleColor": "#b4c8d8", "titleFontSize": 12, "titleOpacity": 0.8, "titleX": 0, "titleY": -7}, "field": "y", "scale": {"domain": [80, 140]}, "sort": [], "type": "quantitative"}}}, {"mark": {"type": "line", "color": "#36B7B4"}, "data": {"url": "https://raw.githubusercontent.com/EconomicsObservatory/ECOvisualisations/main/articles/how-is-consumer-spending-around-christmas-2023-likely-to-affect-retailers/data/fig6_food.csv"}, "encoding": {"x": {"field": "time", "type": "temporal"}, "y": {"field": "Volume", "type": "quantitative"}}}, {"mark": {"type": "line", "color": "#F4134D"}, "data": {"url": "https://raw.githubusercontent.com/EconomicsObservatory/ECOvisualisations/main/articles/how-is-consumer-spending-around-christmas-2023-likely-to-affect-retailers/data/fig6_food.csv"}, "encoding": {"x": {"field": "time", "type": "temporal"}, "y": {"field": "Value", "type": "quantitative"}}}, {"mark": {"type": "text", "align": "left", "color": "#F4134D", "dx": 5, "fontSize": 12, "text": "Value"}, "data": {"url": "https://raw.githubusercontent.com/EconomicsObservatory/ECOvisualisations/main/articles/how-is-consumer-spending-around-christmas-2023-likely-to-affect-retailers/data/fig6_food.csv"}, "encoding": {"x": {"field": "time", "type": "temporal"}, "y": {"field": "Value", "type": "quantitative"}}, "transform": [{"filter": "datum.time>toDate('2023-09-01')"}]}, {"mark": {"type": "text", "align": "left", "color": "#36B7B4", "dx": 5, "fontSize": 12, "text": "Volume"}, "data": {"url": "https://raw.githubusercontent.com/EconomicsObservatory/ECOvisualisations/main/articles/how-is-consumer-spending-around-christmas-2023-likely-to-affect-retailers/data/fig6_food.csv"}, "encoding": {"x": {"field": "time", "type": "temporal"}, "y": {"field": "Volume", "type": "quantitative"}}, "transform": [{"filter": "datum.time>toDate('2023-09-01')"}]}, {"mark": {"type": "image", "align": "right", "baseline": "top", "height": 40, "opacity": 0.5, "width": 40, "xOffset": 0, "yOffset": -33}, "data": {"name": "data-a6e300cdca6f0e0f794a21cab52e7c0b"}, "encoding": {"url": {"field": "img", "type": "nominal"}, "x": {"field": "x", "type": "temporal"}, "y": {"field": "y", "type": "quantitative"}}}], "background": "#122B39", "datasets": {"data-f14e0a1e1aeb5bf7618cf53004727dc9": [{"x": "2019-10-01", "y": 100}, {"x": "2023-10-01", "y": 100}], "data-a6e300cdca6f0e0f794a21cab52e7c0b": [{"x": "2023-10-01", "y": 140, "img": "https://raw.githubusercontent.com/EconomicsObservatory/ECOvisualisations/main/guidelines/logos/eco-icon-light.png"}]}, "height": 300, "title": "", "width": 400, "$schema": "https://vega.github.io/schema/vega-lite/v5.16.3.json"}