{"config": {"view": {"continuousWidth": 400, "continuousHeight": 300, "stroke": null}}, "data": {"url": "https://raw.githubusercontent.com/EconomicsObservatory/ECOvisualisations/main/articles/what-have-two-years-of-interrupted-schooling-taught-us-about-learning/data/fig2_inequality.csv"}, "mark": {"type": "point", "size": 25}, "encoding": {"color": {"field": "duration", "scale": {"range": ["#36B7B4", "#F4134D", "#0063AF"]}, "type": "nominal"}, "column": {"field": "inequality", "sort": [], "title": "Inequality", "type": "nominal"}, "fill": {"field": "duration", "legend": {"title": "Duration"}, "scale": {"range": ["#36B7B4", "#F4134D", "#0063AF"]}, "type": "nominal"}, "shape": {"field": "subject", "legend": {"title": "Subject"}, "type": "nominal"}, "x": {"axis": {"domainColor": "#676A86", "grid": false, "labelAngle": 0, "labelColor": "#676A86", "orient": "bottom", "tickColor": "#676A86", "tickCount": 10, "title": "", "titleAlign": "center", "titleAnchor": "middle", "titleColor": "#676A86", "titleX": 207, "titleY": -15}, "field": "grade", "scale": {"domain": [1, 9]}, "sort": [], "type": "quantitative"}, "y": {"axis": null, "field": "value", "stack": true, "type": "quantitative"}}, "height": 300, "title": "", "width": 100, "$schema": "https://vega.github.io/schema/vega-lite/v4.17.0.json"}