{"config": {"view": {"continuousWidth": 400, "continuousHeight": 300, "stroke": null}}, "layer": [{"mark": {"type": "line", "color": "#0063AF"}, "encoding": {"x": {"axis": {"domainColor": "#676A86", "grid": false, "labelAngle": 0, "labelColor": "#676A86", "orient": "bottom", "tickColor": "#676A86", "tickCount": 10, "title": "", "titleAlign": "center", "titleAnchor": "middle", "titleColor": "#676A86", "titleX": 207, "titleY": -15}, "field": "date", "sort": [], "type": "temporal"}, "y": {"axis": {"domainColor": "#676A86", "grid": false, "labelColor": "#676A86", "tickColor": "#676A86", "title": "\u00a3 billion, adjusted for inflation, 2019 constant prices", "titleAlign": "left", "titleAngle": 0, "titleBaseline": "bottom", "titleColor": "#676A86", "titleX": -5, "titleY": -5}, "field": "bi", "scale": {"domain": [25, 65]}, "sort": [], "type": "quantitative"}}, "transform": [{"calculate": "timeParse(replace(replace(replace(replace(datum.yearq, 'Q1', '02'), 'Q2', '05'),  'Q3', '08'), 'Q4', '11'), '%Y %m')", "as": "date"}]}, {"mark": {"type": "line", "color": "#36B7B4"}, "encoding": {"x": {"axis": {"domainColor": "#676A86", "grid": false, "labelAngle": 0, "labelColor": "#676A86", "orient": "bottom", "tickColor": "#676A86", "tickCount": 10, "title": "", "titleAlign": "center", "titleAnchor": "middle", "titleColor": "#676A86", "titleX": 207, "titleY": -15}, "field": "date", "sort": [], "type": "temporal"}, "y": {"field": "ci", "type": "quantitative"}}, "transform": [{"calculate": "timeParse(replace(replace(replace(replace(datum.yearq, 'Q1', '02'), 'Q2', '05'),  'Q3', '08'), 'Q4', '11'), '%Y %m')", "as": "date"}]}, {"mark": {"type": "line", "color": "#36B7B4", "strokeDash": [5, 5]}, "encoding": {"x": {"axis": {"domainColor": "#676A86", "grid": false, "labelAngle": 0, "labelColor": "#676A86", "orient": "bottom", "tickColor": "#676A86", "tickCount": 10, "title": "", "titleAlign": "center", "titleAnchor": "middle", "titleColor": "#676A86", "titleX": 207, "titleY": -15}, "field": "date", "sort": [], "type": "temporal"}, "y": {"field": "it", "type": "quantitative"}}, "transform": [{"calculate": "timeParse(replace(replace(replace(replace(datum.yearq, 'Q1', '02'), 'Q2', '05'),  'Q3', '08'), 'Q4', '11'), '%Y %m')", "as": "date"}]}, {"mark": {"type": "rule", "color": "#676A86", "opacity": 0.5}, "encoding": {"x": {"axis": {"domainColor": "#676A86", "grid": false, "labelAngle": 0, "labelColor": "#676A86", "orient": "bottom", "tickColor": "#676A86", "tickCount": 10, "title": "", "titleAlign": "center", "titleAnchor": "middle", "titleColor": "#676A86", "titleX": 207, "titleY": -15}, "field": "date", "sort": [], "type": "temporal"}}, "transform": [{"calculate": "timeParse(replace(replace(replace(replace(datum.yearq, 'Q1', '02'), 'Q2', '05'),  'Q3', '08'), 'Q4', '11'), '%Y %m')", "as": "date"}, {"filter": "datum.yearq==\"2016 Q1\""}]}, {"mark": {"type": "text", "color": "#0063AF", "text": "Business investment", "yOffset": 30}, "encoding": {"x": {"axis": {"domainColor": "#676A86", "grid": false, "labelAngle": 0, "labelColor": "#676A86", "orient": "bottom", "tickColor": "#676A86", "tickCount": 10, "title": "", "titleAlign": "center", "titleAnchor": "middle", "titleColor": "#676A86", "titleX": 207, "titleY": -15}, "field": "date", "sort": [], "type": "temporal"}, "y": {"axis": {"domainColor": "#676A86", "grid": false, "labelColor": "#676A86", "tickColor": "#676A86", "title": "\u00a3 billion, adjusted for inflation, 2019 constant prices", "titleAlign": "left", "titleAngle": 0, "titleBaseline": "bottom", "titleColor": "#676A86", "titleX": -5, "titleY": -5}, "field": "bi", "scale": {"domain": [25, 65]}, "sort": [], "type": "quantitative"}}, "transform": [{"calculate": "timeParse(replace(replace(replace(replace(datum.yearq, 'Q1', '02'), 'Q2', '05'),  'Q3', '08'), 'Q4', '11'), '%Y %m')", "as": "date"}, {"filter": "datum.yearq==\"2010 Q1\""}]}, {"mark": {"type": "text", "color": "#36B7B4", "text": "Counterfactual investment", "yOffset": -20}, "encoding": {"x": {"axis": {"domainColor": "#676A86", "grid": false, "labelAngle": 0, "labelColor": "#676A86", "orient": "bottom", "tickColor": "#676A86", "tickCount": 10, "title": "", "titleAlign": "center", "titleAnchor": "middle", "titleColor": "#676A86", "titleX": 207, "titleY": -15}, "field": "date", "sort": [], "type": "temporal"}, "y": {"field": "ci", "type": "quantitative"}}, "transform": [{"calculate": "timeParse(replace(replace(replace(replace(datum.yearq, 'Q1', '02'), 'Q2', '05'),  'Q3', '08'), 'Q4', '11'), '%Y %m')", "as": "date"}, {"filter": "datum.yearq==\"2019 Q1\""}]}, {"mark": {"type": "text", "color": "#36B7B4", "text": "Memo: Investment trend", "yOffset": -45}, "encoding": {"x": {"axis": {"domainColor": "#676A86", "grid": false, "labelAngle": 0, "labelColor": "#676A86", "orient": "bottom", "tickColor": "#676A86", "tickCount": 10, "title": "", "titleAlign": "center", "titleAnchor": "middle", "titleColor": "#676A86", "titleX": 207, "titleY": -15}, "field": "date", "sort": [], "type": "temporal"}, "y": {"field": "it", "type": "quantitative"}}, "transform": [{"calculate": "timeParse(replace(replace(replace(replace(datum.yearq, 'Q1', '02'), 'Q2', '05'),  'Q3', '08'), 'Q4', '11'), '%Y %m')", "as": "date"}, {"filter": "datum.yearq==\"2009 Q1\""}]}], "data": {"name": "data-c4f32895c42ca448f1ece47d512a48c9"}, "height": 300, "title": "", "width": 400, "$schema": "https://vega.github.io/schema/vega-lite/v4.17.0.json", "datasets": {"data-c4f32895c42ca448f1ece47d512a48c9": [{"yearq": "1997 Q1", "bi": 34.459, "ci": null, "it": 38.33730826099262}, {"yearq": "1997 Q2", "bi": 36.59, "ci": null, "it": 38.52899480229758}, {"yearq": "1997 Q3", "bi": 38.553, "ci": null, "it": 38.72163977630906}, {"yearq": "1997 Q4", "bi": 39.381, "ci": null, "it": 38.91524797519061}, {"yearq": "1998 Q1", "bi": 40.131, "ci": null, "it": 39.10982421506655}, {"yearq": "1998 Q2", "bi": 40.076, "ci": null, "it": 39.305373336141884}, {"yearq": "1998 Q3", "bi": 40.382, "ci": null, "it": 39.50190020282259}, {"yearq": "1998 Q4", "bi": 41.537, "ci": null, "it": 39.69940970383669}, {"yearq": "1999 Q1", "bi": 41.265, "ci": null, "it": 39.89790675235588}, {"yearq": "1999 Q2", "bi": 40.07, "ci": null, "it": 40.09739628611766}, {"yearq": "1999 Q3", "bi": 41.842, "ci": null, "it": 40.297883267548244}, {"yearq": "1999 Q4", "bi": 41.032, "ci": null, "it": 40.49937268388598}, {"yearq": "2000 Q1", "bi": 42.352, "ci": null, "it": 40.70186954730541}, {"yearq": "2000 Q2", "bi": 45.295, "ci": null, "it": 40.90537889504193}, {"yearq": "2000 Q3", "bi": 41.682, "ci": null, "it": 41.10990578951713}, {"yearq": "2000 Q4", "bi": 42.942, "ci": null, "it": 41.31545531846471}, {"yearq": "2001 Q1", "bi": 43.406, "ci": null, "it": 41.52203259505703}, {"yearq": "2001 Q2", "bi": 43.756, "ci": null, "it": 41.729642758032305}, {"yearq": "2001 Q3", "bi": 42.468, "ci": null, "it": 41.93829097182246}, {"yearq": "2001 Q4", "bi": 40.803, "ci": null, "it": 42.14798242668157}, {"yearq": "2002 Q1", "bi": 40.955, "ci": null, "it": 42.35872233881497}, {"yearq": "2002 Q2", "bi": 41.724, "ci": null, "it": 42.57051595050904}, {"yearq": "2002 Q3", "bi": 42.162, "ci": null, "it": 42.78336853026158}, {"yearq": "2002 Q4", "bi": 44.386, "ci": null, "it": 42.99728537291289}, {"yearq": "2003 Q1", "bi": 44.686, "ci": null, "it": 43.212271799777454}, {"yearq": "2003 Q2", "bi": 42.132, "ci": null, "it": 43.42833315877634}, {"yearq": "2003 Q3", "bi": 41.647, "ci": null, "it": 43.645474824570215}, {"yearq": "2003 Q4", "bi": 41.2, "ci": null, "it": 43.86370219869306}, {"yearq": "2004 Q1", "bi": 42.41, "ci": null, "it": 44.08302070968653}, {"yearq": "2004 Q2", "bi": 39.385, "ci": null, "it": 44.30343581323495}, {"yearq": "2004 Q3", "bi": 40.693, "ci": null, "it": 44.524952992301124}, {"yearq": "2004 Q4", "bi": 41.34, "ci": null, "it": 44.747577757262626}, {"yearq": "2005 Q1", "bi": 41.134, "ci": null, "it": 44.971315646048936}, {"yearq": "2005 Q2", "bi": 47.87, "ci": null, "it": 45.196172224279174}, {"yearq": "2005 Q3", "bi": 43.229, "ci": null, "it": 45.42215308540056}, {"yearq": "2005 Q4", "bi": 43.053, "ci": null, "it": 45.64926385082756}, {"yearq": "2006 Q1", "bi": 44.821, "ci": null, "it": 45.87751017008169}, {"yearq": "2006 Q2", "bi": 44.357, "ci": null, "it": 46.106897720932096}, {"yearq": "2006 Q3", "bi": 47.146, "ci": null, "it": 46.33743220953675}, {"yearq": "2006 Q4", "bi": 46.483, "ci": null, "it": 46.56911937058443}, {"yearq": "2007 Q1", "bi": 48.33, "ci": null, "it": 46.80196496743735}, {"yearq": "2007 Q2", "bi": 49.98, "ci": null, "it": 47.03597479227453}, {"yearq": "2007 Q3", "bi": 47.41, "ci": null, "it": 47.271154666235894}, {"yearq": "2007 Q4", "bi": 50.882, "ci": null, "it": 47.50751043956707}, {"yearq": "2008 Q1", "bi": 46.96, "ci": null, "it": 47.7450479917649}, {"yearq": "2008 Q2", "bi": 48.736, "ci": null, "it": 47.98377323172372}, {"yearq": "2008 Q3", "bi": 46.893, "ci": null, "it": 48.223692097882335}, {"yearq": "2008 Q4", "bi": 45.311, "ci": null, "it": 48.46481055837174}, {"yearq": "2009 Q1", "bi": 41.006, "ci": null, "it": 48.707134611163596}, {"yearq": "2009 Q2", "bi": 39.114, "ci": null, "it": 48.950670284219406}, {"yearq": "2009 Q3", "bi": 38.306, "ci": null, "it": 49.1954236356405}, {"yearq": "2009 Q4", "bi": 38.165, "ci": null, "it": 49.4414007538187}, {"yearq": "2010 Q1", "bi": 39.649, "ci": null, "it": 49.68860775758779}, {"yearq": "2010 Q2", "bi": 39.513, "ci": null, "it": 49.93705079637572}, {"yearq": "2010 Q3", "bi": 40.874, "ci": null, "it": 50.18673605035759}, {"yearq": "2010 Q4", "bi": 43.603, "ci": null, "it": 50.43766973060937}, {"yearq": "2011 Q1", "bi": 39.881, "ci": null, "it": 50.689858079262414}, {"yearq": "2011 Q2", "bi": 41.641, "ci": null, "it": 50.94330736965872}, {"yearq": "2011 Q3", "bi": 43.46, "ci": null, "it": 51.198023906507004}, {"yearq": "2011 Q4", "bi": 44.769, "ci": null, "it": 51.45401402603954}, {"yearq": "2012 Q1", "bi": 45.733, "ci": null, "it": 51.71128409616973}, {"yearq": "2012 Q2", "bi": 42.982, "ci": null, "it": 51.96984051665057}, {"yearq": "2012 Q3", "bi": 43.643, "ci": null, "it": 52.22968971923382}, {"yearq": "2012 Q4", "bi": 46.382, "ci": null, "it": 52.49083816782998}, {"yearq": "2013 Q1", "bi": 44.472, "ci": null, "it": 52.75329235866913}, {"yearq": "2013 Q2", "bi": 45.474, "ci": null, "it": 53.017058820462466}, {"yearq": "2013 Q3", "bi": 47.039, "ci": null, "it": 53.28214411456477}, {"yearq": "2013 Q4", "bi": 47.528, "ci": null, "it": 53.548554835137594}, {"yearq": "2014 Q1", "bi": 47.583, "ci": null, "it": 53.816297609313274}, {"yearq": "2014 Q2", "bi": 48.81, "ci": null, "it": 54.085379097359834}, {"yearq": "2014 Q3", "bi": 49.288, "ci": null, "it": 54.35580599284663}, {"yearq": "2014 Q4", "bi": 49.947, "ci": null, "it": 54.62758502281086}, {"yearq": "2015 Q1", "bi": 52.826, "ci": null, "it": 54.900722947924905}, {"yearq": "2015 Q2", "bi": 52.481, "ci": null, "it": 55.17522656266453}, {"yearq": "2015 Q3", "bi": 52.51, "ci": null, "it": 55.45110269547784}, {"yearq": "2015 Q4", "bi": 55.404, "ci": null, "it": 55.72835820895523}, {"yearq": "2016 Q1", "bi": 56.007, "ci": 56.007, "it": 56.007}, {"yearq": "2016 Q2", "bi": 55.985, "ci": 56.287034999999996, "it": null}, {"yearq": "2016 Q3", "bi": 56.89, "ci": 56.56847017499999, "it": null}, {"yearq": "2016 Q4", "bi": 54.364, "ci": 56.85131252587498, "it": null}, {"yearq": "2017 Q1", "bi": 55.84, "ci": 57.13556908850435, "it": null}, {"yearq": "2017 Q2", "bi": 56.661, "ci": 57.42124693394686, "it": null}, {"yearq": "2017 Q3", "bi": 56.21, "ci": 57.70835316861659, "it": null}, {"yearq": "2017 Q4", "bi": 56.964, "ci": 57.99689493445966, "it": null}, {"yearq": "2018 Q1", "bi": 56.481, "ci": 58.286879409131956, "it": null}, {"yearq": "2018 Q2", "bi": 55.124, "ci": 58.57831380617761, "it": null}, {"yearq": "2018 Q3", "bi": 55.252, "ci": 58.87120537520849, "it": null}, {"yearq": "2018 Q4", "bi": 55.493, "ci": 59.16556140208452, "it": null}, {"yearq": "2019 Q1", "bi": 55.769, "ci": 59.46138920909494, "it": null}, {"yearq": "2019 Q2", "bi": 55.923, "ci": 59.758696155140406, "it": null}, {"yearq": "2019 Q3", "bi": 56.569, "ci": 60.057489635916106, "it": null}, {"yearq": "2019 Q4", "bi": 56.999, "ci": 60.35777708409568, "it": null}, {"yearq": "2020 Q1", "bi": 55.477, "ci": 59.04787915532654, "it": null}, {"yearq": "2020 Q2", "bi": 43.963, "ci": 47.08799876102026, "it": null}, {"yearq": "2020 Q3", "bi": 48.806, "ci": 52.51069117162178, "it": null}, {"yearq": "2020 Q4", "bi": 50.167, "ci": 54.2375533330607, "it": null}, {"yearq": "2021 Q1", "bi": 47.578, "ci": 51.70966948732553, "it": null}, {"yearq": "2021 Q2", "bi": 50.602, "ci": 55.25482173845025, "it": null}, {"yearq": "2021 Q3", "bi": 51.731, "ci": 56.76390667957423, "it": null}, {"yearq": "2021 Q4", "bi": 50.326, "ci": 55.50603382572263, "it": null}, {"yearq": "2022 Q1", "bi": 50.916, "ci": 56.43429244450303, "it": null}, {"yearq": "2022 Q2", "bi": 53.737, "ci": 59.84320479340052, "it": null}, {"yearq": "2022 Q3", "bi": 52.398, "ci": 58.651268516004144, "it": null}, {"yearq": "2022 Q4", "bi": 51.69607250000001, "ci": 58.15882810906572, "it": null}]}}