{"config": {"view": {"continuousWidth": 400, "continuousHeight": 300, "stroke": null}}, "layer": [{"mark": "errorbar", "encoding": {"color": {"condition": {"value": "#243B5A", "test": "datum['2018']>datum['2019']"}, "value": "#243B5A"}, "x": {"type": "quantitative", "field": "2018", "title": "%"}, "x2": {"field": "2019"}, "y": {"type": "nominal", "field": "employees", "title": ""}}, "transform": [{"pivot": "year", "value": "value", "groupby": ["employees"]}]}, {"mark": {"type": "point", "color": "#36B7B4", "fill": "#36B7B4", "opacity": 0.8, "size": 40}, "encoding": {"x": {"type": "quantitative", "axis": {"domainColor": "#676A86", "grid": false, "labelColor": "#676A86", "tickColor": "#676A86", "title": "%", "titleAnchor": "end", "titleColor": "#676A86", "titleY": -15}, "field": "value", "title": ""}, "y": {"type": "nominal", "axis": null, "field": "employees", "sort": []}}, "transform": [{"filter": "datum.year==2018"}]}, {"mark": {"type": "point", "color": "#243B5A", "fill": "#243B5A", "opacity": 0.8, "size": 40}, "encoding": {"x": {"type": "quantitative", "axis": {"domainColor": "#676A86", "grid": false, "labelColor": "#676A86", "tickColor": "#676A86", "title": "%", "titleAnchor": "end", "titleColor": "#676A86", "titleY": -15}, "field": "value", "title": ""}, "y": {"type": "nominal", "axis": null, "field": "employees", "sort": []}}, "transform": [{"filter": "datum.year==2019"}]}, {"mark": {"type": "point", "angle": 210, "color": "#243B5A", "fill": "#243B5A", "opacity": 0.8, "shape": "triangle", "size": 5, "xOffset": -7}, "encoding": {"x": {"type": "quantitative", "axis": {"domainColor": "#676A86", "grid": false, "labelColor": "#676A86", "tickColor": "#676A86", "title": "%", "titleAnchor": "end", "titleColor": "#676A86", "titleY": -15}, "field": "value", "title": ""}, "y": {"type": "nominal", "axis": null, "field": "employees", "sort": []}}, "transform": [{"filter": "datum.year==2019"}, {"filter": {"field": "employees", "oneOf": ["10 to 49 employees", "1000 or more employees"]}}]}, {"mark": {"type": "point", "angle": 30, "color": "#243B5A", "fill": "#243B5A", "opacity": 0.8, "shape": "triangle", "size": 5, "xOffset": 7}, "encoding": {"text": {"type": "nominal", "field": "employees"}, "x": {"type": "quantitative", "axis": {"domainColor": "#676A86", "grid": false, "labelColor": "#676A86", "tickColor": "#676A86", "title": "%", "titleAnchor": "end", "titleColor": "#676A86", "titleY": -15}, "field": "value", "title": ""}, "y": {"type": "nominal", "axis": null, "field": "employees", "sort": []}}, "transform": [{"filter": "datum.year==2019"}, {"filter": {"field": "employees", "oneOf": ["All businesses", "250 to 999 employees", "0 to 9 employees", "50 to 249 employees"]}}, {"filter": "datum.year==2019"}]}, {"mark": {"type": "text", "align": "right", "color": "#676A86", "size": 10, "xOffset": -10}, "encoding": {"text": {"type": "nominal", "field": "employees"}, "x": {"type": "quantitative", "axis": {"domainColor": "#676A86", "grid": false, "labelColor": "#676A86", "tickColor": "#676A86", "title": "%", "titleAnchor": "end", "titleColor": "#676A86", "titleY": -15}, "field": "value", "title": ""}, "y": {"type": "nominal", "axis": null, "field": "employees", "sort": []}}, "transform": [{"filter": "datum.year==2018"}, {"filter": {"field": "employees", "oneOf": ["10 to 49 employees", "1000 or more employees"]}}]}, {"mark": {"type": "text", "align": "right", "color": "#676A86", "size": 10, "xOffset": -10}, "encoding": {"text": {"type": "nominal", "field": "employees"}, "x": {"type": "quantitative", "axis": {"domainColor": "#676A86", "grid": false, "labelColor": "#676A86", "tickColor": "#676A86", "title": "%", "titleAnchor": "end", "titleColor": "#676A86", "titleY": -15}, "field": "value", "title": ""}, "y": {"type": "nominal", "axis": null, "field": "employees", "sort": []}}, "transform": [{"filter": "datum.year==2019"}, {"filter": {"field": "employees", "oneOf": ["All businesses", "250 to 999 employees", "0 to 9 employees", "50 to 249 employees"]}}]}, {"data": {"name": "data-09330e3b79468df4fc846a0ca99154f3"}, "mark": {"type": "text", "align": "left", "baseline": "middle", "size": 10, "yOffset": -26}, "encoding": {"color": {"type": "nominal", "field": "c", "scale": null}, "text": {"type": "nominal", "field": "t"}, "x": {"type": "quantitative", "field": "x"}, "y": {"type": "nominal", "field": "y"}}}, {"data": {"url": "https://raw.githubusercontent.com/EconomicsObservatory/ECOvisualisations/main/articles/2021-05-26-update-are-small-businesses-ready-to-compete-as-consumers-move-online/data/fig1_employees.csv"}, "mark": {"type": "text", "align": "center", "color": "#36B7B4", "size": 10, "yOffset": 12}, "encoding": {"text": {"type": "nominal", "field": "value"}, "x": {"type": "quantitative", "axis": {"domainColor": "#676A86", "grid": false, "labelColor": "#676A86", "tickColor": "#676A86", "title": "%", "titleAnchor": "end", "titleColor": "#676A86", "titleY": -15}, "field": "value", "title": ""}, "y": {"type": "nominal", "axis": null, "field": "employees", "sort": []}}, "transform": [{"filter": "datum.year==2018"}]}, {"data": {"url": "https://raw.githubusercontent.com/EconomicsObservatory/ECOvisualisations/main/articles/2021-05-26-update-are-small-businesses-ready-to-compete-as-consumers-move-online/data/fig1_employees.csv"}, "mark": {"type": "text", "align": "center", "color": "#243B5A", "size": 10, "yOffset": -11}, "encoding": {"text": {"type": "nominal", "field": "value"}, "x": {"type": "quantitative", "axis": {"domainColor": "#676A86", "grid": false, "labelColor": "#676A86", "tickColor": "#676A86", "title": "%", "titleAnchor": "end", "titleColor": "#676A86", "titleY": -15}, "field": "value", "title": ""}, "y": {"type": "nominal", "axis": null, "field": "employees", "sort": []}}, "transform": [{"filter": "datum.year==2019"}]}], "data": {"url": "https://raw.githubusercontent.com/EconomicsObservatory/ECOvisualisations/main/articles/2021-05-26-update-are-small-businesses-ready-to-compete-as-consumers-move-online/data/fig1_employees.csv"}, "height": 200, "title": "", "width": 400, "$schema": "https://vega.github.io/schema/vega-lite/v4.8.1.json", "datasets": {"data-09330e3b79468df4fc846a0ca99154f3": [{"x": 51.0, "y": "10 to 49 employees", "t": "2018", "c": "#36B7B4"}, {"x": 54.8, "y": "10 to 49 employees", "t": " \u27a1 2019", "c": "#243B5A"}]}}