{"config": {"view": {"continuousWidth": 400, "continuousHeight": 300, "stroke": null}}, "layer": [{"data": {"name": "data-e6b0006a1a4398b6c84aa504d32cbf9c"}, "mark": {"type": "area", "color": "#36B7B4", "opacity": 0.1}, "encoding": {"x": {"field": "x", "type": "quantitative"}, "y": {"field": "y", "type": "quantitative"}, "y2": {"field": "y2"}}}, {"data": {"name": "data-7cdf07c8a1ccef755d11b325b06ea1c6"}, "mark": {"type": "area", "color": "#F4134D", "opacity": 0.1}, "encoding": {"x": {"field": "x", "type": "quantitative"}, "y": {"field": "y", "type": "quantitative"}, "y2": {"field": "y2"}}}, {"data": {"name": "data-97de206f2f2de740c2b1f17036719984"}, "mark": {"type": "line", "color": "#676A86", "strokeDash": [5, 5], "strokeWidth": 1}, "encoding": {"x": {"field": "x", "sort": [], "type": "quantitative"}, "y": {"field": "y", "type": "quantitative"}}}, {"data": {"url": "https://raw.githubusercontent.com/EconomicsObservatory/ECOvisualisations/main/articles/three-centuries-of-uk-business-cycles-what-lessons-for-today/data/fig3_mpc.csv"}, "mark": {"type": "line", "color": "#179FDB"}, "encoding": {"color": {"field": "quarter", "legend": null, "type": "nominal"}, "x": {"axis": {"domainColor": "#676A86", "format": ".0f", "grid": false, "labelAngle": 0, "labelColor": "#676A86", "orient": "bottom", "tickColor": "#676A86", "tickCount": 4, "title": "quarters from peak \u27a1", "titleAlign": "center", "titleAnchor": "middle", "titleColor": "#676A86", "titleX": 277, "titleY": -15}, "field": "dt", "sort": [], "type": "quantitative"}, "y": {"axis": {"domainColor": "#676A86", "grid": false, "labelColor": "#676A86", "tickColor": "#676A86", "title": "Deviation from peak (%)", "titleAlign": "left", "titleAngle": 0, "titleBaseline": "bottom", "titleColor": "#676A86", "titleX": -5, "titleY": -5}, "field": "value", "sort": [], "type": "quantitative"}}}, {"data": {"url": "https://raw.githubusercontent.com/EconomicsObservatory/ECOvisualisations/main/articles/three-centuries-of-uk-business-cycles-what-lessons-for-today/data/fig3_mpc.csv"}, "mark": {"type": "text", "align": "left", "dx": 5}, "encoding": {"color": {"field": "quarter", "legend": null, "type": "nominal"}, "text": {"field": "quarter", "type": "nominal"}, "x": {"axis": {"domainColor": "#676A86", "format": ".0f", "grid": false, "labelAngle": 0, "labelColor": "#676A86", "orient": "bottom", "tickColor": "#676A86", "tickCount": 4, "title": "quarters from peak \u27a1", "titleAlign": "center", "titleAnchor": "middle", "titleColor": "#676A86", "titleX": 277, "titleY": -15}, "field": "dt", "sort": [], "type": "quantitative"}, "y": {"axis": {"domainColor": "#676A86", "grid": false, "labelColor": "#676A86", "tickColor": "#676A86", "title": "Deviation from peak (%)", "titleAlign": "left", "titleAngle": 0, "titleBaseline": "bottom", "titleColor": "#676A86", "titleX": -5, "titleY": -5}, "field": "value", "sort": [], "type": "quantitative"}}, "transform": [{"filter": "datum.dt==20"}, {"filter": "datum.quarter!=\"1973Q2\""}]}, {"data": {"url": "https://raw.githubusercontent.com/EconomicsObservatory/ECOvisualisations/main/articles/three-centuries-of-uk-business-cycles-what-lessons-for-today/data/fig3_mpc.csv"}, "mark": {"type": "text", "align": "left", "dx": 5, "dy": 12}, "encoding": {"color": {"field": "quarter", "legend": null, "type": "nominal"}, "text": {"field": "quarter", "type": "nominal"}, "x": {"axis": {"domainColor": "#676A86", "format": ".0f", "grid": false, "labelAngle": 0, "labelColor": "#676A86", "orient": "bottom", "tickColor": "#676A86", "tickCount": 4, "title": "quarters from peak \u27a1", "titleAlign": "center", "titleAnchor": "middle", "titleColor": "#676A86", "titleX": 277, "titleY": -15}, "field": "dt", "sort": [], "type": "quantitative"}, "y": {"axis": {"domainColor": "#676A86", "grid": false, "labelColor": "#676A86", "tickColor": "#676A86", "title": "Deviation from peak (%)", "titleAlign": "left", "titleAngle": 0, "titleBaseline": "bottom", "titleColor": "#676A86", "titleX": -5, "titleY": -5}, "field": "value", "sort": [], "type": "quantitative"}}, "transform": [{"filter": "datum.dt==20"}, {"filter": "datum.quarter==\"1973Q2\""}]}, {"data": {"url": "https://raw.githubusercontent.com/EconomicsObservatory/ECOvisualisations/main/articles/three-centuries-of-uk-business-cycles-what-lessons-for-today/data/fig3_mpc.csv"}, "mark": {"type": "line", "stroke": "#179FDB", "strokeWidth": 3}, "encoding": {"color": {"field": "quarter", "legend": null, "type": "nominal"}, "x": {"axis": {"domainColor": "#676A86", "format": ".0f", "grid": false, "labelAngle": 0, "labelColor": "#676A86", "orient": "bottom", "tickColor": "#676A86", "tickCount": 4, "title": "quarters from peak \u27a1", "titleAlign": "center", "titleAnchor": "middle", "titleColor": "#676A86", "titleX": 277, "titleY": -15}, "field": "dt", "sort": [], "type": "quantitative"}, "y": {"axis": {"domainColor": "#676A86", "grid": false, "labelColor": "#676A86", "tickColor": "#676A86", "title": "Deviation from peak (%)", "titleAlign": "left", "titleAngle": 0, "titleBaseline": "bottom", "titleColor": "#676A86", "titleX": -5, "titleY": -5}, "field": "value", "sort": [], "type": "quantitative"}}, "transform": [{"filter": "datum.quarter==\"2022Q2\""}]}, {"data": {"name": "data-901a1c184f677bc46880c3180ed0fd22"}, "mark": {"type": "text", "align": "left", "color": "#179FDB", "dx": 5, "fontWeight": "bold"}, "encoding": {"text": {"field": "t", "type": "nominal"}, "x": {"field": "x", "type": "quantitative"}, "y": {"field": "y", "type": "quantitative"}}}], "height": 300, "title": "", "width": 400, "$schema": "https://vega.github.io/schema/vega-lite/v4.17.0.json", "datasets": {"data-e6b0006a1a4398b6c84aa504d32cbf9c": [{"x": 0, "y": 0, "y2": 6}, {"x": 20, "y": 0, "y2": 6}], "data-7cdf07c8a1ccef755d11b325b06ea1c6": [{"x": 0, "y": 0, "y2": -7}, {"x": 20, "y": 0, "y2": -7}], "data-97de206f2f2de740c2b1f17036719984": [{"x": 0, "y": 0}, {"x": 20, "y": 0}], "data-901a1c184f677bc46880c3180ed0fd22": [{"x": 13.5, "y": -3.4, "t": "2022Q2 MPR Forecast"}, {"x": 13.5, "y": -4.1, "t": "Market Interest Rates"}]}}