[{"id": "East Lothian", "pop": 20.01}, {"id": "Edinburgh", "pop": 17.66}, {"id": "West Lothian", "pop": 17.05}, {"id": "Orkney", "pop": 16.12}, {"id": "Aberdeenshire", "pop": 14.87}, {"id": "Midlothian", "pop": 14.84}, {"id": "Highland", "pop": 12.58}, {"id": "Perth and Kinross", "pop": 12.55}, {"id": "Falkirk", "pop": 11.0}, {"id": "Moray", "pop": 10.37}, {"id": "Glasgow", "pop": 10.16}, {"id": "Stirling", "pop": 9.19}, {"id": "Scottish Borders", "pop": 8.46}, {"id": "Scotland", "pop": 7.96}, {"id": "East Renfrewshire", "pop": 7.88}, {"id": "Fife", "pop": 7.4}, {"id": "Aberdeen", "pop": 7.37}, {"id": "Clackmannanshire", "pop": 6.48}, {"id": "Angus", "pop": 6.4}, {"id": "North Lanarkshire", "pop": 6.15}, {"id": "South Lanarkshire", "pop": 6.14}, {"id": "Renfrewshire", "pop": 3.29}, {"id": "Shetland", "pop": 3.11}, {"id": "Dundee", "pop": 1.51}, {"id": "East Ayrshire", "pop": 1.23}, {"id": "Dumfries and Galloway", "pop": 0.51}, {"id": "East Dunbartonshire", "pop": 0.12}, {"id": "South Ayrshire", "pop": -0.13}, {"id": "Eilean Siar", "pop": -1.08}, {"id": "North Ayrshire", "pop": -1.55}, {"id": "West Dunbartonshire", "pop": -5.95}, {"id": "Argyll and Bute", "pop": -6.17}, {"id": "Inverclyde", "pop": -8.98}]