{"config": {"view": {"continuousWidth": 400, "continuousHeight": 300, "stroke": null}}, "layer": [{"data": {"name": "data-ddc142b90b6c65aa9e363784c02e89ae"}, "mark": {"type": "area", "color": "#179FDB", "opacity": 0.1}, "encoding": {"x": {"field": "x", "sort": [], "type": "quantitative"}, "y": {"axis": {"domainColor": "#676A86", "format": ".0f", "grid": false, "labelColor": "#676A86", "tickColor": "#676A86", "title": "%", "titleAlign": "left", "titleAngle": 0, "titleBaseline": "bottom", "titleColor": "#676A86", "titleX": -5, "titleY": -5}, "field": "y", "scale": {"domain": [90, 100]}, "sort": [], "type": "quantitative"}, "y2": {"field": "y2"}}}, {"data": {"url": "https://raw.githubusercontent.com/EconomicsObservatory/ECOvisualisations/main/articles/what-are-the-big-policy-challenges-facing-scotlands-new-first-minister/data/fig3_earnings.csv"}, "mark": {"type": "line", "color": "#179FDB"}, "encoding": {"x": {"axis": {"domainColor": "#676A86", "format": ".0f", "grid": false, "labelAngle": 0, "labelColor": "#676A86", "orient": "bottom", "tickColor": "#676A86", "tickCount": 10, "title": "tax year 2027/28", "titleAlign": "right", "titleAnchor": "end", "titleColor": "#676A86", "titleY": -15}, "field": "year", "sort": [], "type": "quantitative"}, "y": {"axis": {"domainColor": "#676A86", "format": ".0f", "grid": false, "labelColor": "#676A86", "tickColor": "#676A86", "title": "\u00a3 million", "titleAlign": "left", "titleAngle": 0, "titleBaseline": "bottom", "titleColor": "#676A86", "titleX": -5, "titleY": -5}, "field": "earnings", "scale": {"domain": [90, 100]}, "sort": [], "type": "quantitative"}}}, {"data": {"url": "https://raw.githubusercontent.com/EconomicsObservatory/ECOvisualisations/main/articles/what-are-the-big-policy-challenges-facing-scotlands-new-first-minister/data/fig3_earnings.csv"}, "mark": {"type": "line", "color": "#676A86"}, "encoding": {"x": {"axis": {"domainColor": "#676A86", "format": ".0f", "grid": false, "labelAngle": 0, "labelColor": "#676A86", "orient": "bottom", "tickColor": "#676A86", "tickCount": 10, "title": "tax year 2027/28", "titleAlign": "right", "titleAnchor": "end", "titleColor": "#676A86", "titleY": -15}, "field": "year", "sort": [], "type": "quantitative"}, "y": {"field": "p14", "sort": [], "type": "quantitative"}}}, {"data": {"name": "data-60f84d2d59d92d4969cdb8ac4b39aaef"}, "mark": {"type": "text", "align": "right"}, "encoding": {"color": {"field": "t", "legend": null, "scale": {"range": ["#179FDB", "#676A86", "#179FDB"]}, "type": "nominal"}, "text": {"field": "t", "type": "nominal"}, "x": {"field": "x", "sort": [], "type": "quantitative"}, "y": {"field": "y", "sort": [], "type": "quantitative"}}}], "height": 300, "title": "", "width": 400, "$schema": "https://vega.github.io/schema/vega-lite/v4.17.0.json", "datasets": {"data-ddc142b90b6c65aa9e363784c02e89ae": [{"x": 2022, "y": 90, "y2": 100}, {"x": 2028, "y": 90, "y2": 100}], "data-60f84d2d59d92d4969cdb8ac4b39aaef": [{"x": 2018.0, "y": 98.5, "t": "Scottish nominal average earnings as a share of UK"}, {"x": 2027.0, "y": 96.2, "t": "Pre-2014 average of share"}, {"x": 2026.6, "y": 99.6, "t": "Forecast"}]}}